prayer_times_calculator_offline/__init__.py
prayer_times_calculator_offline/exceptions.py
prayer_times_calculator_offline/interop.py
prayer_times_calculator_offline/methods.py
prayer_times_calculator_offline/praytimes.py
prayer_times_calculator_offline-1.0.2.dist-info/LICENSE
prayer_times_calculator_offline-1.0.2.dist-info/METADATA
prayer_times_calculator_offline-1.0.2.dist-info/WHEEL
prayer_times_calculator_offline-1.0.2.dist-info/top_level.txt
prayer_times_calculator_offline-1.0.2.dist-info/RECORD
