Metadata-Version: 2.1
Name: prayer_times_calculator_offline
Version: 1.0.2
Summary: Prayer Times Calculator - Offline
Author-email: "cpfair, Umair Chagani" <cpf@cpfx.ca>
License: MIT
Project-URL: Homepage, https://github.com/cfair/prayer-times-calculator-offline
License-File: LICENSE
